bipackage/__init__.py
bipackage/autocomplete.py
bipackage/cli/_entry.py
bipackage/configs/bwa_dedup.json
bipackage/configs/cnv.json
bipackage/configs/cnv_pon.json
bipackage/configs/gatk_gcnv.json
bipackage/configs/snv_indel.json
bipackage/constants.py
bipackage/pipelines/__init__.py
bipackage/pipelines/_pipentry.py
bipackage/pipelines/aligners/__init__.py
bipackage/pipelines/aligners/bwa_dedup_sp_qc_mosdepth.py
bipackage/pipelines/defaults.py
bipackage/pipelines/germline/__init__.py
bipackage/pipelines/germline/gatk_gcnv_json.py
bipackage/pipelines/somatic/__init__.py
bipackage/pipelines/somatic/cnv.py
bipackage/pipelines/somatic/pon.py
bipackage/pipelines/somatic/snv_indel.py
bipackage/src/__init__.py
bipackage/src/bamtools/__init__.py
bipackage/src/bamtools/bam_counts.py
bipackage/src/bamtools/compile_bam_stats.py
bipackage/src/bedtools/__init__.py
bipackage/src/bedtools/bedfilegenerator.py
bipackage/src/bedtools/panelgenequery.py
bipackage/src/bedtools/panelgenequery_old.py
bipackage/src/fastqtools/__init__.py
bipackage/src/fastqtools/downsample.py
bipackage/src/fastqtools/fastq_read_counter.py
bipackage/src/fastqtools/fastqvalidate.py
bipackage/src/fastqtools/merge_it.py
bipackage/src/fastqtools/remove_undetermined_fastq.py
bipackage/src/fastqtools/undetermined_demultiplexer.py
bipackage/src/ittools/__init__.py
bipackage/src/ittools/ismount.py
bipackage/src/ittools/md5sumchecker_multi.py
bipackage/src/ittools/truncatedfchecker_single.py
bipackage/src/nipttools/__init__.py
bipackage/src/nipttools/nipt_bcl2fastq.py
bipackage/util/_colors.py
bipackage/util/aliaser.py
bipackage/util/utilities.py
bipackage-0.2.6.dist-info/entry_points.txt
bipackage-0.2.6.dist-info/METADATA
bipackage-0.2.6.dist-info/WHEEL
bipackage-0.2.6.dist-info/RECORD
