Metadata-Version: 2.3
Name: bipackage
Version: 0.2.6
Summary: Bioinformatics tools package
Author: ZK
Requires-Python: >=3.10
Classifier: Programming Language :: Python :: 3
Classifier: Programming Language :: Python :: 3.10
Classifier: Programming Language :: Python :: 3.11
Classifier: Programming Language :: Python :: 3.12
Classifier: Programming Language :: Python :: 3.13
Requires-Dist: argcomplete (>=3.6.2,<4.0.0)
Requires-Dist: biopython (>=1.85,<2.0)
Requires-Dist: pandas (>=2.2.3,<3.0.0)
Requires-Dist: requests (>=2.32.4,<3.0.0)
Requires-Dist: rich-argparse (>=1.7.0,<2.0.0)
